pandasai_openai/__init__.py
pandasai_openai/azure_openai.py
pandasai_openai/base.py
pandasai_openai/openai.py
pandasai_openai-0.1.5.dist-info/METADATA
pandasai_openai-0.1.5.dist-info/WHEEL
pandasai_openai-0.1.5.dist-info/RECORD
